{
    "type": "GenericCrafter",
    "name": "Fuel mixer",
    "description": "Combines chemichal stuff tohegether to make rocket fuel",
    "outputItem": {"item": "rocket-fuel", "amount":1},
    "size": 1,
    "itemCapacity": 25,
    "health": 45,
    "hasPower": true,
    "hasItems": true,
    "craftTime": 785,
    "drawer": {
        "type": "DrawMulti",
        "drawers": [
            {"type": "DrawDefault"},
            {"type": "DrawRegion",
                "suffix": "-rotator",
                "rotateSpeed": 2,
                "spinSprite": false
            }]
    },
    "updateEffect": "steam",
    "consumes":{
        "power": 3.15,
        "liquids": [
           {"liquid": "oil", "amount": 0.07}
            ],
        "items": {
            "items":[
                {"item": "thorium", "amount": 15},
                {"item": "titanium-alloy", "amount": 2}
                ]
    }
},
"requirements": [
    {"item": "scheme", "amount":5},
    {"item": "titanium-alloy", "amount": 45},
    {"item": "pneumatic-component", "amount": 10}
    ],
    "category": "crafting",
    "research": "silicon-smelter",
    "idleSound": "respawning",
    "idleSoundVolume": 0.7
    }